{"cameraMode":{"drawMode":0,"name":"Shaded","section":"Shading Mode"},"sceneLighting":true,"audioPlay":false,"sceneViewState":{"showFog":true,"showMaterialUpdate":false,"showSkybox":true,"showFlares":true,"showImageEffects":true,"showParticleSystems":true},"in2DMode":false,"pivot":{"x":0.03066849708557129,"y":0.7383506298065186,"z":-0.201790452003479},"rotation":{"x":0.08613843470811844,"y":0.8425058126449585,"z":-0.14158989489078523,"w":0.5125587582588196},"size":4.095346927642822,"orthographic":false}